akshara/__init__.py
akshara/sutrakaarya.py
akshara/varna.py
akshara/varna_compiler.py
akshara/varnakaarya.py
akshara/resources/latest.csv
akshara/resources/laukika.csv
akshara/resources/moola.csv
akshara/resources/varna.yml
akshara/resources/vistrita.csv
akshara/resources/vividha.yml
akshara/sutra/sutra.json
akshara-1.1.3.dist-info/LICENSE
akshara-1.1.3.dist-info/METADATA
akshara-1.1.3.dist-info/WHEEL
akshara-1.1.3.dist-info/top_level.txt
akshara-1.1.3.dist-info/RECORD
