Metadata-Version: 2.1
Name: akshara
Version: 1.1.3
Summary: A project to help spelling in Sanskrit (Devanaagari)
Home-page: https://github.com/arindamsaha1507/akshara
Author: Arindam Saha
Author-email: arindamsaha1507@gmail.com
License: GNU GENERAL PUBLIC LICENSE
Classifier: Programming Language :: Python :: 3
Classifier: License :: OSI Approved :: GNU General Public License (GPL)
Classifier: Operating System :: OS Independent
Classifier: Topic :: Text Processing :: Linguistic
License-File: LICENSE
Requires-Dist: pyyaml
